apache_license_check.py
apache_license_check-1.0.0.dist-info/METADATA
apache_license_check-1.0.0.dist-info/WHEEL
apache_license_check-1.0.0.dist-info/entry_points.txt
apache_license_check-1.0.0.dist-info/top_level.txt
apache_license_check-1.0.0.dist-info/RECORD
