Metadata-Version: 2.1
Name: apache-license-check
Version: 1.0.0
Summary: CLI tool to check source files for Apache License headers.
Home-page: https://faculty.ai/
Author: Faculty
Author-email: opensource@faculty.ai
License: Apache Software License
Project-URL: GitHub, https://github.com/facultyai/apache-license-check
Platform: UNKNOWN
Requires-Dist: termcolor
